{
  "config": {
    "title": "Tfs Portal",
    "description": "My awesome app using docz",
    "menu": [],
    "version": "0.1.0",
    "repository": null,
    "native": false,
    "codeSandbox": true,
    "themeConfig": {
      "logo": {
        "src": "/public/images/logo.png",
        "width": 150
      }
    },
    "separator": "-",
    "htmlContext": {
      "favicon": "/public/images/icon_totvs.png"
    }
  },
  "props": [
    {
      "key": "src/App.js",
      "value": [
        {
          "description": "",
          "displayName": "App",
          "methods": [],
          "actualName": "App"
        }
      ]
    },
    {
      "key": "src/components/Button/Button.js",
      "value": [
        {
          "description": "",
          "displayName": "Button",
          "methods": [],
          "actualName": "Button"
        }
      ]
    }
  ],
  "entries": [
    {
      "key": "src/components/Button/button.mdx",
      "value": {
        "name": "Button",
        "menu": "Components",
        "id": "c3a4162ba271ddbeabea462f799cd4e0",
        "filepath": "src/components/Button/button.mdx",
        "link": "",
        "slug": "src-components-button-button",
        "route": "/src-components-button-button",
        "headings": [
          {
            "slug": "hello-world",
            "depth": 1,
            "value": "Hello world"
          }
        ]
      }
    },
    {
      "key": "src/docs/developers/git.md",
      "value": {
        "name": "Git",
        "route": "/git",
        "menu": "Developers",
        "id": "f7deafbeb199c15b4807a7f5987cdfa4",
        "filepath": "src/docs/developers/git.md",
        "link": "",
        "slug": "src-docs-developers-git",
        "headings": [
          {
            "slug": "git",
            "depth": 1,
            "value": "Git"
          },
          {
            "slug": "introdução",
            "depth": 2,
            "value": "Introdução"
          },
          {
            "slug": "fluxos",
            "depth": 2,
            "value": "Fluxos"
          },
          {
            "slug": "regras-para-criação-da-branch",
            "depth": 2,
            "value": "Regras para criação da  Branch"
          },
          {
            "slug": "regras-para-criação-de-commits",
            "depth": 2,
            "value": "Regras para criação de  Commits"
          },
          {
            "slug": "tipo",
            "depth": 3,
            "value": "Tipo"
          },
          {
            "slug": "escopo",
            "depth": 3,
            "value": "Escopo"
          },
          {
            "slug": "descrição-curta",
            "depth": 3,
            "value": "Descrição curta"
          },
          {
            "slug": "corpo",
            "depth": 3,
            "value": "Corpo"
          },
          {
            "slug": "rodapé",
            "depth": 3,
            "value": "Rodapé"
          },
          {
            "slug": "breaking-changes",
            "depth": 3,
            "value": "Breaking Changes"
          },
          {
            "slug": "exemplos-de-descrições-de-commits-completos",
            "depth": 3,
            "value": "Exemplos de descrições de  commits  completos"
          },
          {
            "slug": "regras-para-criação-de-pull-requests",
            "depth": 2,
            "value": "Regras para criação de  Pull Requests"
          },
          {
            "slug": "componente",
            "depth": 3,
            "value": "Componente"
          },
          {
            "slug": "número-da-issue",
            "depth": 3,
            "value": "Número da ISSUE"
          },
          {
            "slug": "pr-checklist",
            "depth": 3,
            "value": "PR Checklist"
          },
          {
            "slug": "qual-o-comportamento-atual",
            "depth": 3,
            "value": "Qual o comportamento atual?"
          },
          {
            "slug": "qual-o-novo-comportamento",
            "depth": 3,
            "value": "Qual o novo comportamento?"
          },
          {
            "slug": "simulação",
            "depth": 3,
            "value": "Simulação"
          }
        ]
      }
    },
    {
      "key": "src/docs/developers/react-native.mdx",
      "value": {
        "name": "React Native",
        "route": "/reactNative",
        "menu": "Developers",
        "id": "44953632ca137c148c979f92a5f55d36",
        "filepath": "src/docs/developers/react-native.mdx",
        "link": "",
        "slug": "src-docs-developers-react-native",
        "headings": [
          {
            "slug": "react-native",
            "depth": 1,
            "value": "React Native"
          },
          {
            "slug": "introdução",
            "depth": 2,
            "value": "Introdução"
          },
          {
            "slug": "estrutura-de-projetos",
            "depth": 2,
            "value": "Estrutura de Projetos"
          },
          {
            "slug": "boas-práticas",
            "depth": 2,
            "value": "Boas Práticas"
          },
          {
            "slug": "erros-comuns",
            "depth": 2,
            "value": "Erros Comuns"
          },
          {
            "slug": "deploy",
            "depth": 2,
            "value": "Deploy"
          }
        ]
      }
    },
    {
      "key": "src/docs/developers/java.mdx",
      "value": {
        "name": "Java",
        "route": "/java",
        "menu": "Developers",
        "id": "bcf9b9038ef75a4ec6ddd5546db47b88",
        "filepath": "src/docs/developers/java.mdx",
        "link": "",
        "slug": "src-docs-developers-java",
        "headings": [
          {
            "slug": "java",
            "depth": 1,
            "value": "Java"
          },
          {
            "slug": "introdução",
            "depth": 2,
            "value": "Introdução"
          },
          {
            "slug": "estrutura-de-projetos",
            "depth": 2,
            "value": "Estrutura de Projetos"
          },
          {
            "slug": "boas-práticas",
            "depth": 2,
            "value": "Boas Práticas"
          },
          {
            "slug": "erros-comuns",
            "depth": 2,
            "value": "Erros Comuns"
          },
          {
            "slug": "deploy",
            "depth": 2,
            "value": "Deploy"
          }
        ]
      }
    },
    {
      "key": "src/docs/developers/reactjs.mdx",
      "value": {
        "name": "React JS",
        "route": "/reactjs",
        "menu": "Developers",
        "id": "21d95539ade803f50d90a81afdf8d4e9",
        "filepath": "src/docs/developers/reactjs.mdx",
        "link": "",
        "slug": "src-docs-developers-reactjs",
        "headings": [
          {
            "slug": "react-js",
            "depth": 1,
            "value": "React JS"
          },
          {
            "slug": "introdução",
            "depth": 2,
            "value": "Introdução"
          },
          {
            "slug": "estrutura-de-projetos",
            "depth": 2,
            "value": "Estrutura de Projetos"
          },
          {
            "slug": "boas-práticas",
            "depth": 2,
            "value": "Boas Práticas"
          },
          {
            "slug": "erros-comuns",
            "depth": 2,
            "value": "Erros Comuns"
          },
          {
            "slug": "deploy",
            "depth": 2,
            "value": "Deploy"
          }
        ]
      }
    },
    {
      "key": "src/docs/structure/projects.mdx",
      "value": {
        "name": "Estrutura",
        "route": "/structure",
        "menu": "Estrutura",
        "id": "f47b8af653352179938e10b205a5a5f2",
        "filepath": "src/docs/structure/projects.mdx",
        "link": "",
        "slug": "src-docs-structure-projects",
        "headings": [
          {
            "slug": "estrutura",
            "depth": 1,
            "value": "Estrutura"
          },
          {
            "slug": "data-transfer-object-dtos",
            "depth": 2,
            "value": "DATA TRANSFER OBJECT (DTO)S"
          },
          {
            "slug": "entidades",
            "depth": 3,
            "value": "Entidades"
          },
          {
            "slug": "estrutura-dtos",
            "depth": 3,
            "value": "Estrutura DTO's"
          },
          {
            "slug": "regras",
            "depth": 4,
            "value": "Regras"
          },
          {
            "slug": "integradores",
            "depth": 2,
            "value": "INTEGRADORES"
          }
        ]
      }
    },
    {
      "key": "src/docs/documentation/document-settings.mdx",
      "value": {
        "name": "Bem vindo",
        "route": "/",
        "id": "0437236ad998f9f7af89acf467ed58f9",
        "filepath": "src/docs/documentation/document-settings.mdx",
        "link": "",
        "slug": "src-docs-documentation-document-settings",
        "menu": "",
        "headings": [
          {
            "slug": "documentação",
            "depth": 1,
            "value": "Documentação"
          },
          {
            "slug": "sobre-a-documentação",
            "depth": 2,
            "value": "Sobre a Documentação"
          },
          {
            "slug": "navegação",
            "depth": 2,
            "value": "Navegação"
          },
          {
            "slug": "algo-faltando",
            "depth": 2,
            "value": "Algo faltando?"
          },
          {
            "slug": "comentários",
            "depth": 2,
            "value": "Comentários"
          }
        ]
      }
    },
    {
      "key": "src/docs/documentation/challenge.mdx",
      "value": {
        "name": "Desafio",
        "route": "/challenge",
        "menu": "Projetos",
        "id": "0b311d3aeb3f2aa372036a31649e9c5d",
        "filepath": "src/docs/documentation/challenge.mdx",
        "link": "",
        "slug": "src-docs-documentation-challenge",
        "headings": [
          {
            "slug": "desafio",
            "depth": 1,
            "value": "Desafio"
          },
          {
            "slug": "construir-a-página-do-administrador",
            "depth": 2,
            "value": "Construir a Página do administrador."
          },
          {
            "slug": "construir-o-aplicativo-do-usuário",
            "depth": 2,
            "value": "Construir o aplicativo do usuário"
          },
          {
            "slug": "requisitos",
            "depth": 2,
            "value": "Requisitos:"
          },
          {
            "slug": "ganhe-mais-pontos",
            "depth": 2,
            "value": "Ganhe mais pontos:"
          },
          {
            "slug": "submissão",
            "depth": 2,
            "value": "Submissão:"
          },
          {
            "slug": "prazo-de-entrega-sugerido",
            "depth": 2,
            "value": "Prazo de entrega sugerido:"
          }
        ]
      }
    },
    {
      "key": "src/docs/documentation/pfin.md",
      "value": {
        "name": "PFin",
        "route": "/pfin",
        "menu": "Projetos",
        "id": "3cd6a30cf30cec28b911822a9e241f76",
        "filepath": "src/docs/documentation/pfin.md",
        "link": "",
        "slug": "src-docs-documentation-pfin",
        "headings": [
          {
            "slug": "configurações",
            "depth": 1,
            "value": "Configurações"
          },
          {
            "slug": "variáveis-de-ambiente-react",
            "depth": 2,
            "value": "Variáveis de ambiente REACT"
          },
          {
            "slug": "variáveis-de-ambiente-android",
            "depth": 2,
            "value": "Variáveis de ambiente Android"
          },
          {
            "slug": "configuração-de-aplicações-java",
            "depth": 2,
            "value": "Configuração de aplicações JAVA"
          },
          {
            "slug": "desabilitar-segurança-do-chrome",
            "depth": 2,
            "value": "Desabilitar segurança do chrome"
          },
          {
            "slug": "instalar-dependências-reactive-native",
            "depth": 2,
            "value": "Instalar dependências Reactive Native"
          },
          {
            "slug": "iniciar-app-no-android",
            "depth": 2,
            "value": "Iniciar APP no Android"
          },
          {
            "slug": "correção-de-problemas",
            "depth": 2,
            "value": "Correção de problemas"
          },
          {
            "slug": "system-limit-for-number-of-file-watchers-reached",
            "depth": 3,
            "value": "System limit for number of file watchers reached"
          },
          {
            "slug": "configuração-de-hosts",
            "depth": 2,
            "value": "Configuração de hosts"
          },
          {
            "slug": "instalar-apk-no-emulador",
            "depth": 2,
            "value": "Instalar APK no emulador"
          },
          {
            "slug": "gerar-apk-android",
            "depth": 2,
            "value": "Gerar APK Android"
          }
        ]
      }
    },
    {
      "key": "src/docs/documentation/projects.mdx",
      "value": {
        "name": "Internet Banking",
        "route": "/ib",
        "menu": "Projetos",
        "id": "06ed6693f494a988c509a53f5e0c43ac",
        "filepath": "src/docs/documentation/projects.mdx",
        "link": "",
        "slug": "src-docs-documentation-projects",
        "headings": [
          {
            "slug": "projeto-intenet-banking",
            "depth": 1,
            "value": "Projeto Intenet Banking"
          },
          {
            "slug": "palavras-chave",
            "depth": 2,
            "value": "Palavras-chave"
          },
          {
            "slug": "importante",
            "depth": 2,
            "value": "IMPORTANTE**"
          },
          {
            "slug": "para-novos-releases",
            "depth": 2,
            "value": "Para novos  releases"
          },
          {
            "slug": "react-native",
            "depth": 3,
            "value": "REACT NATIVE"
          },
          {
            "slug": "ios",
            "depth": 4,
            "value": "iOS"
          },
          {
            "slug": "android",
            "depth": 4,
            "value": "ANDROID"
          },
          {
            "slug": "",
            "depth": 1,
            "value": ""
          },
          {
            "slug": "configuração-para-desenvolvimento",
            "depth": 2,
            "value": "Configuração para Desenvolvimento"
          },
          {
            "slug": "configuração-do-ambiente",
            "depth": 3,
            "value": "Configuração do ambiente"
          },
          {
            "slug": "executando-a-aplicação",
            "depth": 3,
            "value": "Executando a aplicação"
          },
          {
            "slug": "android-1",
            "depth": 4,
            "value": "Android"
          },
          {
            "slug": "ios-1",
            "depth": 4,
            "value": "iOS"
          },
          {
            "slug": "gerando-a-release",
            "depth": 3,
            "value": "Gerando a release"
          },
          {
            "slug": "android-2",
            "depth": 4,
            "value": "Android"
          },
          {
            "slug": "ios-2",
            "depth": 4,
            "value": "iOS"
          },
          {
            "slug": "erros-comuns",
            "depth": 2,
            "value": "Erros comuns"
          },
          {
            "slug": "android-3",
            "depth": 3,
            "value": "Android"
          },
          {
            "slug": "android-erro-ao-compilar-o-lottie-react-native-nullpointerexception",
            "depth": 3,
            "value": "(Android) Erro ao compilar o lottie-react-native NullPointerException"
          },
          {
            "slug": "android-algum-erro-ao-gerar-a-release-ou-executar-a-aplicação",
            "depth": 3,
            "value": "(Android) Algum erro ao gerar a release ou executar a aplicação"
          },
          {
            "slug": "ios-algum-erro-ao-gerar-a-release-ou-executar-a-aplicação",
            "depth": 3,
            "value": "(iOS) Algum erro ao gerar a release ou executar a aplicação"
          },
          {
            "slug": "após-alterar-o-arquivo-babelrcjs-ou-o-valor-de-react_app_costumer-o-aplicativo-obtém-os-arquivos-do-valor-anterior",
            "depth": 3,
            "value": "Após alterar o arquivo .babelrc.js ou o valor de REACT_APP_COSTUMER o aplicativo obtém os arquivos do valor anterior"
          },
          {
            "slug": "sugestões",
            "depth": 2,
            "value": "Sugestões"
          },
          {
            "slug": "para-gerenciar-as-versões-do-nodejs-e-npm",
            "depth": 3,
            "value": "Para gerenciar as versões do NodeJS e npm"
          }
        ]
      }
    }
  ]
}
